astley/__init__.py
astley/astley.py
astley-0.0.2.dist-info/LICENSE
astley-0.0.2.dist-info/METADATA
astley-0.0.2.dist-info/WHEEL
astley-0.0.2.dist-info/top_level.txt
astley-0.0.2.dist-info/RECORD
