Metadata-Version: 2.1
Name: astley
Version: 0.0.2
Summary: An exploration into package making.
Home-page: https://github.com/navamivk/Astley
Author: Navami Vipith Kumar
Author-email: navamioct25@gmail.com
License: UNKNOWN
Project-URL: Bug Tracker, https://github.com/navamivk/Astley/issues
Platform: UNKNOWN
Classifier: Programming Language :: Python :: 3
Classifier: License :: OSI Approved :: MIT License
Classifier: Operating System :: OS Independent
Requires-Python: >=3.6
License-File: LICENSE
